randhy/__init__.py
randhy-2.0.2.dist-info/METADATA
randhy-2.0.2.dist-info/RECORD
randhy-2.0.2.dist-info/WHEEL
randhy-2.0.2.dist-info/top_level.txt
