Metadata-Version: 2.1
Name: randhy
Version: 2.0.2
Summary: Approximate randomisation library
Home-page: https://www.github.com/asavkov/randhy/
Author: Sasho Savkov
Author-email: me@sasho.io
License: UNKNOWN
Platform: UNKNOWN
